AUTHORS.rst
CHANGELOG.rst
LICENSE
MANIFEST.in
README.rst
setup.py
django_interim_cms.egg-info/PKG-INFO
django_interim_cms.egg-info/SOURCES.txt
django_interim_cms.egg-info/dependency_links.txt
django_interim_cms.egg-info/not-zip-safe
django_interim_cms.egg-info/requires.txt
django_interim_cms.egg-info/top_level.txt
interim_cms/__init__.py
interim_cms/dashboard.py
interim_cms/forms.py
interim_cms/models.py
interim_cms/modules.py
interim_cms/urls.py
interim_cms/views.py
interim_cms/static/interim_cms/css/cms.css
interim_cms/static/interim_cms/css/skin.css
interim_cms/static/interim_cms/images/._.DS_Store
interim_cms/static/interim_cms/images/caret-double-left-over.png
interim_cms/static/interim_cms/images/caret-double-left.png
interim_cms/static/interim_cms/images/caret-double-right-over.png
interim_cms/static/interim_cms/images/caret-double-right.png
interim_cms/static/interim_cms/js/Chart.min.js
interim_cms/static/interim_cms/js/cms.js
interim_cms/static/interim_cms/js/jquery.cookie.js
interim_cms/templates/admin/base.html
interim_cms/templates/admin/index.html
interim_cms/templates/interim_cms/example_tile.html
interim_cms/templates/interim_cms/graph_tile.html
interim_cms/templates/interim_cms/raw_web_socket_tile.html
interim_cms/templates/interim_cms/welcome.html
interim_cms/templatetags/__init__.py
interim_cms/templatetags/__init__.pyc
interim_cms/templatetags/cms_tags.py
interim_cms/templatetags/cms_tags.pyc